video_snap/__init__.py
video_snap/framesync.py
video_snap/skeleton.py
video_snap/lib/__init__.py
video_snap/lib/utils.py
video_snap/lib/video_frame_faiss_analyser.py
video_snap/lib/video_frame_packet_analyser.py
video_snap/lib/video_frame_ssim_analyser.py
video_snap-0.0.2.dist-info/licenses/LICENSE.txt
video_snap-0.0.2.dist-info/METADATA
video_snap-0.0.2.dist-info/WHEEL
video_snap-0.0.2.dist-info/top_level.txt
video_snap-0.0.2.dist-info/RECORD
